j_builds/__init__.py
j_builds/base.py
j_builds/build.py
j_builds/docker.py
j_builds/git.py
j_builds/printer.py
j_builds-0.0.2.data/scripts/j-build
j_builds-0.0.2.dist-info/LICENSE
j_builds-0.0.2.dist-info/METADATA
j_builds-0.0.2.dist-info/WHEEL
j_builds-0.0.2.dist-info/top_level.txt
j_builds-0.0.2.dist-info/RECORD
