Metadata-Version: 2.1
Name: j-builds
Version: 0.0.2
Summary: Build and Deploy!
Home-page: https://github.com/Spin14/j-builder
Author: Acciaioli Valverde
Author-email: acci.valverde@gmail.com
License: UNKNOWN
Platform: UNKNOWN
Classifier: Programming Language :: Python :: 3.7
Classifier: License :: OSI Approved :: MIT License
Requires-Dist: termcolor
